logflow/cli.py
logflow/devloop.py
logflow/export.py
logflow/history.py
logflow/idea.py
logflow/idea_index.py
logflow/idea_utils.py
logflow/init.py
logflow/listing.py
logflow/note.py
logflow/paths.py
logflow/status.py
logflow/utils.py
logflow_cli-0.1.7.dist-info/LICENSE
logflow_cli-0.1.7.dist-info/METADATA
logflow_cli-0.1.7.dist-info/WHEEL
logflow_cli-0.1.7.dist-info/entry_points.txt
logflow_cli-0.1.7.dist-info/RECORD
