Metadata-Version: 2.3
Name: logflow-cli
Version: 0.1.7
Summary: Focused developer journaling and ideation loop
License: MIT
Keywords: cli,developer-tools,journaling,productivity
Author: Jay Davis
Author-email: 512jay@gmail.com
Maintainer: Oravox LLC
Maintainer-email: oravoxco@gmail.com
Requires-Python: >=3.8
Classifier: License :: OSI Approved :: MIT License
Classifier: Operating System :: OS Independent
Classifier: Programming Language :: Python :: 3
Classifier: Programming Language :: Python :: 3.8
Classifier: Programming Language :: Python :: 3.9
Classifier: Programming Language :: Python :: 3.10
Classifier: Programming Language :: Python :: 3.11
Classifier: Programming Language :: Python :: 3.12
Classifier: Programming Language :: Python :: 3.13
Provides-Extra: fancy-slugs
Provides-Extra: rich
Provides-Extra: slugify
Requires-Dist: python-slugify (>=8.0.0,<9.0.0) ; extra == "fancy-slugs" or extra == "slugify"
Requires-Dist: pyyaml (>=6.0.2,<7.0.0)
Requires-Dist: rich (==13.7.1) ; extra == "rich"
